kelvin/app/__init__.py
kelvin/core/context.py
kelvin/core/application/__init__.py
kelvin/core/application/application.py
kelvin/core/application/data.py
kelvin/core/application/poller.py
kelvin/core/utils/__init__.py
kelvin/sdk/app/__init__.py
kelvin/sdk/app/__main__.py
kelvin/sdk/app/application.py
kelvin/sdk/app/bridge.py
kelvin/sdk/app/common.py
kelvin/sdk/app/config.py
kelvin/sdk/app/context.py
kelvin/sdk/app/data.py
kelvin/sdk/app/file_utils.py
kelvin/sdk/app/logs.py
kelvin/sdk/app/mapping_proxy.py
kelvin/sdk/app/prometheus.py
kelvin/sdk/app/py.typed
kelvin/sdk/app/run.py
kelvin/sdk/app/types.py
kelvin/sdk/app/utils.py
kelvin/sdk/app/version.py
kelvin/sdk/app/cli/__init__.py
kelvin/sdk/app/cli/main.py
kelvin/sdk/app/cli/run.py
kelvin_sdk_app-8.0.5.dist-info/LICENSE.rst
kelvin_sdk_app-8.0.5.dist-info/METADATA
kelvin_sdk_app-8.0.5.dist-info/WHEEL
kelvin_sdk_app-8.0.5.dist-info/entry_points.txt
kelvin_sdk_app-8.0.5.dist-info/top_level.txt
kelvin_sdk_app-8.0.5.dist-info/RECORD
